simulations/alu_1/alu.v
// ============================================================
//  32-BIT RISC ALU  –  IEEE 754 Single-Precision Compliant
//  File    : alu_32.v
//  Desc    : Full ALU – ADD SUB NEG INC DEC
//                       AND OR  XOR NOT
//                       RLC RRC SETC CLRC
// ============================================================
 
module ALU_32 (
    input  wire [31:0] A,        // Operand A (Rs1)
    input  wire [31:0] B,        // Operand B (Rs2 or Imm)
    input  wire        C_in,     // Carry in (from Flags register)
    input  wire [3:0]  ALU_SEL,  // Operation select
 
    output reg  [31:0] Result,   // 32-bit result → Rd
    output reg         C_out,    // Carry out
    output wire        Z_flag,   // Zero   flag
    output wire        N_flag,   // Negative flag
    output reg         V_flag    // Overflow flag
);
 
    // ── ALU_SEL encoding ──────────────────────────────────────
    localparam OP_ADD  = 4'b0000;
    localparam OP_SUB  = 4'b0001;
    localparam OP_NEG  = 4'b0010;
    localparam OP_INC  = 4'b0011;
    localparam OP_DEC  = 4'b0100;
    localparam OP_AND  = 4'b0101;
    localparam OP_OR   = 4'b0110;
    localparam OP_XOR  = 4'b0111;
    localparam OP_NOT  = 4'b1000;
    localparam OP_RLC  = 4'b1001;
    localparam OP_RRC  = 4'b1010;
    localparam OP_SETC = 4'b1011;
    localparam OP_CLRC = 4'b1100;
 
    // 33-bit wires for carry detection
    wire [32:0] A_ext = {1'b0, A};
    wire [32:0] B_ext = {1'b0, B};
    reg  [32:0] Res33;
 
    // ── Continuous flag assignments ───────────────────────────
    assign Z_flag = (Result == 32'h0000_0000);
    assign N_flag = Result[31];  // MSB = sign (IEEE 754 / 2's complement)
 
    // ── Main ALU combinational block ──────────────────────────
    always @(*) begin
        Res33  = 33'b0;
        Result = 32'b0;
        C_out  = 1'b0;
        V_flag = 1'b0;
 
        case (ALU_SEL)
 
            // ── Arithmetic ──────────────────────────────────
            OP_ADD: begin
                Res33  = A_ext + B_ext;
                Result = Res33[31:0];
                C_out  = Res33[32];
                V_flag = (~A[31] & ~B[31] & Result[31]) |
                         ( A[31] &  B[31] & ~Result[31]);
            end
 
            OP_SUB: begin
                Res33  = A_ext - B_ext;
                Result = Res33[31:0];
                C_out  = ~Res33[32];   // C=1 → no borrow (A >= B)
                V_flag = (~A[31] &  B[31] & Result[31]) |
                         ( A[31] & ~B[31] & ~Result[31]);
            end
 
            OP_NEG: begin
                Res33  = {1'b0, ~A} + 33'd1;
                Result = Res33[31:0];
                C_out  = Res33[32];
                V_flag = (A == 32'h8000_0000) ? 1'b1 : 1'b0;
            end
 
            OP_INC: begin
                Res33  = A_ext + 33'd1;
                Result = Res33[31:0];
                C_out  = Res33[32];
                V_flag = (A == 32'h7FFF_FFFF) ? 1'b1 : 1'b0;
            end
 
            OP_DEC: begin
                Res33  = A_ext - 33'd1;
                Result = Res33[31:0];
                C_out  = ~Res33[32];
                V_flag = (A == 32'h8000_0000) ? 1'b1 : 1'b0;
            end
 
            // ── Bitwise Logic ────────────────────────────────
            OP_AND: begin Result = A & B;  C_out = 1'b0; end
            OP_OR:  begin Result = A | B;  C_out = 1'b0; end
            OP_XOR: begin Result = A ^ B;  C_out = 1'b0; end
            OP_NOT: begin Result = ~A;     C_out = 1'b0; end
 
            // ── Rotate through Carry ─────────────────────────
            OP_RLC: begin
                // new[0] = C_in,  new_C = A[31]
                Result = {A[30:0], C_in};
                C_out  = A[31];
            end
 
            OP_RRC: begin
                // new[31] = C_in, new_C = A[0]
                Result = {C_in, A[31:1]};
                C_out  = A[0];
            end
 
            // ── Carry Control ────────────────────────────────
            OP_SETC: begin Result = A; C_out = 1'b1; end
            OP_CLRC: begin Result = A; C_out = 1'b0; end
 
            default: begin Result = 32'b0; C_out = 1'b0; end
        endcase
    end
 
endmodule

simulations/alu_1/dump.vcd
$version Generated by VerilatedVcd $end
$timescale 1ps $end
 $scope module $rootio $end
  $var wire 32 " A [31:0] $end
  $var wire 32 # B [31:0] $end
  $var wire 1 $ C_in $end
  $var wire 4 % ALU_SEL [3:0] $end
  $var wire 32 & Result [31:0] $end
  $var wire 1 ' C_out $end
  $var wire 1 ( Z_flag $end
  $var wire 1 ) N_flag $end
  $var wire 1 * V_flag $end
 $upscope $end
 $scope module ALU_32 $end
  $var wire 32 + A [31:0] $end
  $var wire 32 , B [31:0] $end
  $var wire 1 - C_in $end
  $var wire 4 . ALU_SEL [3:0] $end
  $var wire 32 / Result [31:0] $end
  $var wire 1 0 C_out $end
  $var wire 1 1 Z_flag $end
  $var wire 1 2 N_flag $end
  $var wire 1 3 V_flag $end
  $var wire 4 : OP_ADD [3:0] $end
  $var wire 4 ; OP_SUB [3:0] $end
  $var wire 4 < OP_NEG [3:0] $end
  $var wire 4 = OP_INC [3:0] $end
  $var wire 4 > OP_DEC [3:0] $end
  $var wire 4 ? OP_AND [3:0] $end
  $var wire 4 @ OP_OR [3:0] $end
  $var wire 4 A OP_XOR [3:0] $end
  $var wire 4 B OP_NOT [3:0] $end
  $var wire 4 C OP_RLC [3:0] $end
  $var wire 4 D OP_RRC [3:0] $end
  $var wire 4 E OP_SETC [3:0] $end
  $var wire 4 F OP_CLRC [3:0] $end
  $var wire 33 4 A_ext [32:0] $end
  $var wire 33 6 B_ext [32:0] $end
  $var wire 33 8 Res33 [32:0] $end
 $upscope $end
$enddefinitions $end


#0
b00000000000000000000000000001000 "
b00000000000000000000000000000011 #
0$
b0000 %
b00000000000000000000000000001011 &
0'
0(
0)
0*
b00000000000000000000000000001000 +
b00000000000000000000000000000011 ,
0-
b0000 .
b00000000000000000000000000001011 /
00
01
02
03
b000000000000000000000000000001000 4
b000000000000000000000000000000011 6
b000000000000000000000000000001011 8
b0000 :
b0001 ;
b0010 <
b0011 =
b0100 >
b0101 ?
b0110 @
b0111 A
b1000 B
b1001 C
b1010 D
b1011 E
b1100 F
#2001
b11111111111111111111111111111111 "
b00000000000000000000000000000001 #
b00000000000000000000000000000000 &
1'
1(
b11111111111111111111111111111111 +
b00000000000000000000000000000001 ,
b00000000000000000000000000000000 /
10
11
b011111111111111111111111111111111 4
b000000000000000000000000000000001 6
b100000000000000000000000000000000 8
#4002
b01111111111111111111111111111111 "
b10000000000000000000000000000000 &
0'
0(
1)
1*
b01111111111111111111111111111111 +
b10000000000000000000000000000000 /
00
01
12
13
b001111111111111111111111111111111 4
b010000000000000000000000000000000 8
#6003
b10000000000000000000000000000000 "
b11111111111111111111111111111111 #
b01111111111111111111111111111111 &
1'
0)
b10000000000000000000000000000000 +
b11111111111111111111111111111111 ,
b01111111111111111111111111111111 /
10
02
b010000000000000000000000000000000 4
b011111111111111111111111111111111 6
b101111111111111111111111111111111 8
#8004
b00000000000000000000000000000000 "
b00000000000000000000000000000000 #
b00000000000000000000000000000000 &
0'
1(
0*
b00000000000000000000000000000000 +
b00000000000000000000000000000000 ,
b00000000000000000000000000000000 /
00
11
03
b000000000000000000000000000000000 4
b000000000000000000000000000000000 6
b000000000000000000000000000000000 8
#10005
b00000000000000000000000000001010 "
b00000000000000000000000000000100 #
b0001 %
b00000000000000000000000000000110 &
1'
0(
b00000000000000000000000000001010 +
b00000000000000000000000000000100 ,
b0001 .
b00000000000000000000000000000110 /
10
01
b000000000000000000000000000001010 4
b000000000000000000000000000000100 6
b000000000000000000000000000000110 8
#12006
b00000000000000000000000000000011 "
b00000000000000000000000000000101 #
b11111111111111111111111111111110 &
0'
1)
b00000000000000000000000000000011 +
b00000000000000000000000000000101 ,
b11111111111111111111111111111110 /
00
12
b000000000000000000000000000000011 4
b000000000000000000000000000000101 6
b111111111111111111111111111111110 8
#14007
b10101011110011010001001000110100 "
b10101011110011010001001000110100 #
b00000000000000000000000000000000 &
1'
1(
0)
b10101011110011010001001000110100 +
b10101011110011010001001000110100 ,
b00000000000000000000000000000000 /
10
11
02
b010101011110011010001001000110100 4
b010101011110011010001001000110100 6
b000000000000000000000000000000000 8
#16008
b10000000000000000000000000000000 "
b00000000000000000000000000000001 #
b01111111111111111111111111111111 &
0(
1*
b10000000000000000000000000000000 +
b00000000000000000000000000000001 ,
b01111111111111111111111111111111 /
01
13
b010000000000000000000000000000000 4
b000000000000000000000000000000001 6
b001111111111111111111111111111111 8
#18009
b01111111111111111111111111111111 "
b11111111111111111111111111111111 #
b10000000000000000000000000000000 &
0'
1)
b01111111111111111111111111111111 +
b11111111111111111111111111111111 ,
b10000000000000000000000000000000 /
00
12
b001111111111111111111111111111111 4
b011111111111111111111111111111111 6
b110000000000000000000000000000000 8
#20010
b00000000000000000000000000000101 "
b00000000000000000000000000000000 #
b0010 %
b11111111111111111111111111111011 &
0*
b00000000000000000000000000000101 +
b00000000000000000000000000000000 ,
b0010 .
b11111111111111111111111111111011 /
03
b000000000000000000000000000000101 4
b000000000000000000000000000000000 6
b011111111111111111111111111111011 8
#22011
b00000000000000000000000000000000 "
b00000000000000000000000000000000 &
1'
1(
0)
b00000000000000000000000000000000 +
b00000000000000000000000000000000 /
10
11
02
b000000000000000000000000000000000 4
b100000000000000000000000000000000 8
#24012
b10000000000000000000000000000000 "
b10000000000000000000000000000000 &
0'
0(
1)
1*
b10000000000000000000000000000000 +
b10000000000000000000000000000000 /
00
01
12
13
b010000000000000000000000000000000 4
b010000000000000000000000000000000 8
#26013
b00000000000000000000000000000111 "
b0011 %
b00000000000000000000000000001000 &
0)
0*
b00000000000000000000000000000111 +
b0011 .
b00000000000000000000000000001000 /
02
03
b000000000000000000000000000000111 4
b000000000000000000000000000001000 8
#28014
b11111111111111111111111111111111 "
b00000000000000000000000000000000 &
1'
1(
b11111111111111111111111111111111 +
b00000000000000000000000000000000 /
10
11
b011111111111111111111111111111111 4
b100000000000000000000000000000000 8
#30015
b01111111111111111111111111111111 "
b10000000000000000000000000000000 &
0'
0(
1)
1*
b01111111111111111111111111111111 +
b10000000000000000000000000000000 /
00
01
12
13
b001111111111111111111111111111111 4
b010000000000000000000000000000000 8
#32016
b00000000000000000000000000001000 "
b0100 %
b00000000000000000000000000000111 &
1'
0)
0*
b00000000000000000000000000001000 +
b0100 .
b00000000000000000000000000000111 /
10
02
03
b000000000000000000000000000001000 4
b000000000000000000000000000000111 8
#34017
b00000000000000000000000000000000 "
b11111111111111111111111111111111 &
0'
1)
b00000000000000000000000000000000 +
b11111111111111111111111111111111 /
00
12
b000000000000000000000000000000000 4
b111111111111111111111111111111111 8
#36018
b10000000000000000000000000000000 "
b01111111111111111111111111111111 &
1'
0)
1*
b10000000000000000000000000000000 +
b01111111111111111111111111111111 /
10
02
13
b010000000000000000000000000000000 4
b001111111111111111111111111111111 8
#38019
b00000000000000000000000000000001 "
b00000000000000000000000000000000 &
1(
0*
b00000000000000000000000000000001 +
b00000000000000000000000000000000 /
11
03
b000000000000000000000000000000001 4
b000000000000000000000000000000000 8
#40020
b11111111000000001111111100000000 "
b00001111000011110000111100001111 #
b0101 %
b00001111000000000000111100000000 &
0'
0(
b11111111000000001111111100000000 +
b00001111000011110000111100001111 ,
b0101 .
b00001111000000000000111100000000 /
00
01
b011111111000000001111111100000000 4
b000001111000011110000111100001111 6
#42021
b10101010101010101010101010101010 "
b01010101010101010101010101010101 #
b00000000000000000000000000000000 &
1(
b10101010101010101010101010101010 +
b01010101010101010101010101010101 ,
b00000000000000000000000000000000 /
11
b010101010101010101010101010101010 4
b001010101010101010101010101010101 6
#44022
b11011110101011011011111011101111 "
b11111111111111111111111111111111 #
b11011110101011011011111011101111 &
0(
1)
b11011110101011011011111011101111 +
b11111111111111111111111111111111 ,
b11011110101011011011111011101111 /
01
12
b011011110101011011011111011101111 4
b011111111111111111111111111111111 6
#46023
b11111111000000001111111100000000 "
b00001111000011110000111100001111 #
b0110 %
b11111111000011111111111100001111 &
b11111111000000001111111100000000 +
b00001111000011110000111100001111 ,
b0110 .
b11111111000011111111111100001111 /
b011111111000000001111111100000000 4
b000001111000011110000111100001111 6
#48024
b11001010111111101011101010111110 "
b00000000000000000000000000000000 #
b11001010111111101011101010111110 &
b11001010111111101011101010111110 +
b00000000000000000000000000000000 ,
b11001010111111101011101010111110 /
b011001010111111101011101010111110 4
b000000000000000000000000000000000 6
#50025
b11111111111111111111111111111111 "
b11111111111111111111111111111111 #
b0111 %
b00000000000000000000000000000000 &
1(
0)
b11111111111111111111111111111111 +
b11111111111111111111111111111111 ,
b0111 .
b00000000000000000000000000000000 /
11
02
b011111111111111111111111111111111 4
b011111111111111111111111111111111 6
#52026
b10101010101010101010101010101010 "
b01010101010101010101010101010101 #
b11111111111111111111111111111111 &
0(
1)
b10101010101010101010101010101010 +
b01010101010101010101010101010101 ,
b11111111111111111111111111111111 /
01
12
b010101010101010101010101010101010 4
b001010101010101010101010101010101 6
#54027
b00010010001101000101011001111000 "
b00000000000000000000000000000000 #
b00010010001101000101011001111000 &
0)
b00010010001101000101011001111000 +
b00000000000000000000000000000000 ,
b00010010001101000101011001111000 /
02
b000010010001101000101011001111000 4
b000000000000000000000000000000000 6
#56028
b00000000000000000000000000000000 "
b1000 %
b11111111111111111111111111111111 &
1)
b00000000000000000000000000000000 +
b1000 .
b11111111111111111111111111111111 /
12
b000000000000000000000000000000000 4
#58029
b11111111111111111111111111111111 "
b00000000000000000000000000000000 &
1(
0)
b11111111111111111111111111111111 +
b00000000000000000000000000000000 /
11
02
b011111111111111111111111111111111 4
#60030
b10101010101010101010101010101010 "
b01010101010101010101010101010101 &
0(
b10101010101010101010101010101010 +
b01010101010101010101010101010101 /
01
b010101010101010101010101010101010 4
#62031
b10000000000000000000000000000001 "
b1001 %
b00000000000000000000000000000010 &
1'
b10000000000000000000000000000001 +
b1001 .
b00000000000000000000000000000010 /
10
b010000000000000000000000000000001 4
#64032
b01000000000000000000000000000000 "
1$
b10000000000000000000000000000001 &
0'
1)
b01000000000000000000000000000000 +
1-
b10000000000000000000000000000001 /
00
12
b001000000000000000000000000000000 4
#66033
b00000000000000000000000000000000 "
0$
b00000000000000000000000000000000 &
1(
0)
b00000000000000000000000000000000 +
0-
b00000000000000000000000000000000 /
11
02
b000000000000000000000000000000000 4
#68034
b00000000000000000000000000000001 "
1$
b1010 %
b10000000000000000000000000000000 &
1'
0(
1)
b00000000000000000000000000000001 +
1-
b1010 .
b10000000000000000000000000000000 /
10
01
12
b000000000000000000000000000000001 4
#70035
b10000000000000000000000000000000 "
0$
b01000000000000000000000000000000 &
0'
0)
b10000000000000000000000000000000 +
0-
b01000000000000000000000000000000 /
00
02
b010000000000000000000000000000000 4
#72036
b00000000000000000000000000000011 "
b00000000000000000000000000000001 &
1'
b00000000000000000000000000000011 +
b00000000000000000000000000000001 /
10
b000000000000000000000000000000011 4
#74037
b00010010001101000101011001111000 "
b1011 %
b00010010001101000101011001111000 &
b00010010001101000101011001111000 +
b1011 .
b00010010001101000101011001111000 /
b000010010001101000101011001111000 4
#76038
b1100 %
0'
b1100 .
00
#78039
b00000000000000000000000000000000 "
b1011 %
b00000000000000000000000000000000 &
1'
1(
b00000000000000000000000000000000 +
b1011 .
b00000000000000000000000000000000 /
10
11
b000000000000000000000000000000000 4
#80040
b11011110101011011011111011101111 "
b11001010111111101011101010111110 #
b1101 %
0'
b11011110101011011011111011101111 +
b11001010111111101011101010111110 ,
b1101 .
00
b011011110101011011011111011101111 4
b011001010111111101011101010111110 6
#82040
b1110 %
b1110 .
#84040
b1111 %
b1111 .
#86041
b10000000000000000000000000000000 "
b00000000000000000000000000000000 #
b0000 %
b10000000000000000000000000000000 &
0(
1)
b10000000000000000000000000000000 +
b00000000000000000000000000000000 ,
b0000 .
b10000000000000000000000000000000 /
01
12
b010000000000000000000000000000000 4
b000000000000000000000000000000000 6
b010000000000000000000000000000000 8
#88042
b01111111111111111111111111111111 "
b1000 %
b01111111111111111111111111111111 +
b1000 .
b001111111111111111111111111111111 4
b000000000000000000000000000000000 8
